fmf/__init__.py
fmf/base.py
fmf/cli.py
fmf/context.py
fmf/utils.py
fmf/_compat/__init__.py
fmf/_compat/jsonschema.py
fmf-1.7.0.dist-info/METADATA
fmf-1.7.0.dist-info/WHEEL
fmf-1.7.0.dist-info/entry_points.txt
fmf-1.7.0.dist-info/licenses/LICENSE
fmf-1.7.0.dist-info/RECORD
