Metadata-Version: 2.4
Name: fmf
Version: 1.7.0
Summary: Flexible Metadata Format
Project-URL: homepage, https://github.com/teemtee/fmf
Project-URL: documentation, https://fmf.readthedocs.io
Author-email: Petr Splichal <psplicha@redhat.com>
Maintainer-email: Petr Splichal <psplicha@redhat.com>
License-Expression: GPL-2.0-or-later
License-File: LICENSE
Keywords: metadata,testing
Classifier: Natural Language :: English
Classifier: Programming Language :: Python :: 3.9
Classifier: Programming Language :: Python :: 3.10
Classifier: Programming Language :: Python :: 3.11
Classifier: Programming Language :: Python :: 3.12
Classifier: Topic :: Utilities
Requires-Python: >=3.9
Requires-Dist: filelock
Requires-Dist: jsonschema
Requires-Dist: ruamel-yaml
Provides-Extra: docs
Requires-Dist: sphinx; extra == 'docs'
Requires-Dist: sphinx-rtd-theme; extra == 'docs'
Provides-Extra: tests
Requires-Dist: pytest; extra == 'tests'
